[
  {
    "id": "coinreaders_1759194886_0",
    "title": "[코툰] \"10월, 알트코인 현물 ETF ‘결정의 달’\"",
    "url": "https://www.coinreaders.com/189706",
    "source": "coinreaders",
    "timestamp": "2025-09-30T10:14:46.677384",
    "risk_level": "HIGH",
    "language": "ko",
    "related_coins": [
      "BTC",
      "ETH",
      "DOGE",
      "SHIB",
      "FLOKI",
      "MAGA"
    ],
    "related_influencers": [
      "Gary Gensler"
    ],
    "special_categories": [
      "경제적"
    ],
    "content": "시작페이지로l즐겨찾기lRSSl편집 2025.09.30 [10:00] 전체기사l로그인l회원가입lKOR [코툰] \"10월, 알트코인 현물 ETF ‘결정의 달’\" 오는 10월 다수 알트코인의 현물 ETF 승인 여부를 미국 증권거래위원회(SEC)가 최종 결정할 예정이라고 코인텔레그래프가 전했다. 블룸버그 ETF 애널리스트 제임스 세이파트는 \"10월 2일(현지시간) 커네리 캐피털의 라이트코인(LTC) 현물 ETF를 시작으로 솔라나(SOL), 엑스알피(XRP), 도지코인(DOGE) 등 16개 암호화폐의 현물 ETF 심사 최종 마감일이 예정돼 있다. 이는 향후 몇 주간 ETF 시장에 거대한 이벤트가 될 것”이라고 평가했다."
  },
  {
    "id": "coinreaders_1759194888_1",
    "title": "XRP, ETF 승인 변수 속 7월 패턴 재현하나...'4달러' 시나리오 가동",
    "url": "https://www.coinreaders.com/189698",
    "source": "coinreaders",
    "timestamp": "2025-09-30T10:14:48.182923",
    "risk_level": "HIGH",
    "language": "ko",
    "related_coins": [
      "BTC",
      "ETH",
      "MAGA"
    ],
    "related_influencers": [
      "Gary Gensler"
    ],
    "special_categories": [
      "경제적"
    ],
    "content": "시작페이지로l즐겨찾기lRSSl편집 2025.09.30 [10:00] 전체기사l로그인l회원가입lKOR ▲ 엑스알피(XRP) 엑스알피(XRP)가 7월 돌파와 유사한 차트 패턴을 형성하며 10월 말까지 4달러를 목표로 35% 상승할 가능성이 제기되고, 미국 증권거래위원회의 XRP 현물 ETF 승인 결정이 촉매제 역할을 할 것으로 전망된다. 9월 29일(현지시간) 암호화폐 전문 매체 코인게이프에 따르면, XRP는 하락 채널 내에서 횡보하며 다가오는 촉매제를 평가하고 있다. 차트는 강한 랠리를 만들어낸 7월 돌파 이전과 유사한 구조를 보여주고 있다. 7월 움직임은 66% 랠리를 기록했으며, 저항선이 돌파되면 급격한 급등을 촉발할 수 있음을 보여줬다. 피보나치 확장선은 잠재적 상승 목표를 제시하는데, 1.618 수준은 3.48달러, 2.618 수준은 3.97달러다. 그러나 더 즉각적인 전망은 이번 달 채널이 돌파되면 4달러를 직접 가리키는 35% 랠리를 보여준다. 이는 7월 성과를 반영하며 또 다른 급등 가능성을 강화한다. 2.75달러의 지지선이 최근 하락을 완충하며 강세 진영을 유지하고 있다. 상단 채널 경계에 대한 압력이 증가하면서 XRP는 10월 결정적인 움직임을 보일 준비가 됐다. 10월로 예고된 SEC의 6개의 XRP 현물 ETF 승인 여부 결정은 단기 가격 방향을 크게 좌우할 수 있다. 첫 번째는 10월 18일 그레이스케일 XRP ETF(Grayscale XRP ETF)로, 결과에 따라 초기 변동성을 주입할 수 있다. 하루 뒤인 10월 19일에는 21셰어스 코어 XRP 트러스트(21Shares Core XRP Trust)에 초점이 맞춰지며, 승인될 경우 XRP의 기관 매력에 대한 신뢰를 강화할 수 있다. 10월 20일에는 비트와이즈 XRP ETF(Bitwise XRP ETF)가 검토되며, 승인이 신규 자금 유입을 끌어들일 것으로 기대된다. 10월 23일에는 카나리 캐피털 XRP ETF 마감일이 도래하며, 강세 압력이 주요 저항선 근처에서 지속될 수 있는지 시험한다. 해당 주는 10월 25일 위즈덤트리 XRP ETF(WisdomTree XRP ETF)로 마무리되며, 긍정적인 판결이 10월 거래의 최종 촉매제 역할을 할 수 있다. 차트가 월말까지 4달러를 향한 35% 랠리 가능성을 보여주는 가운데, 결정과 기술적 패턴의 정렬이 중요하게 느껴진다. 10월 활동은 XRP가 마침내 하락 채널을 돌파할지 아니면 또 다른 상승을 지연시킬지 직접적으로 결정할 수 있다. XRP는 기술적 요인과 규제 요인이 모두 정렬되는 결정적인 10월을 맞이하고 있다. 채널 돌파는 7월의 폭발적인 랠리를 반영하고 4달러로 가는 길을 열 것이다. ETF에 대한 여러 증권거래위원회 결정이 돌파를 촉진하거나 저항 장벽을 강화할 수 있다. 10월의 결과는 연말까지 XRP의 궤적을 정의하는 전환점이 될 수 있다. *면책 조항: 이 기사는 투자 참고용으로 이를 근거로 한 투자 손실에 대해 책임을 지지 않습니다. 해당 내용은 정보 제공의 목적으로만 해석되어야 합니다.*"
  },
  {
    "id": "coinreaders_1759194892_5",
    "title": "뉴욕 암호화폐 규제 수장 교체, 시장에 어떤 파장 미칠까",
    "url": "https://www.coinreaders.com/189689",
    "source": "coinreaders",
    "timestamp": "2025-09-30T10:14:52.041832",
    "risk_level": "HIGH",
    "language": "ko",
    "related_coins": [
      "BTC",
      "ETH",
      "DOGE",
      "FLOKI",
      "TRUMP",
      "MAGA"
    ],
    "related_influencers": [
      "Vitalik Buterin"
    ],
    "special_categories": [
      "경제적"
    ],
    "content": "시작페이지로l즐겨찾기lRSSl편집 2025.09.30 [10:00] 전체기사l로그인l회원가입lKOR ▲ 애드리엔 해리스(Adrienne Harris)/출처: 워처구루 © 미국 뉴욕 금융서비스국(DFS) 수퍼인텐던트이자 대표적 암호화폐 규제 책임자인 애드리엔 해리스(Adrienne Harris)가 4년 임기를 마치고 자리에서 물러난다. 이번 사임은 오는 10월부터 공식적으로 효력이 발생한다. 9월 29일(현지시간) 암호화폐 전문매체 워처구루에 따르면, 뉴욕주 캐시 호컬(Kathy Hochul) 주지사는 이날 해리스의 사임을 발표하며 “그녀가 뉴욕 금융시스템을 더 공정하고 투명하게 만드는 데 크게 기여했다”고 평가했다. 해리스는 성명에서 “뉴욕 시민들을 위해 봉사하고, DFS를 글로벌 규제 선도 기관으로 발전시킬 수 있어 영광이었다”고 밝혔다. 호컬 주지사는 후임으로 케이틀린 애스로(Kaitlin Asrow)를 임시 수퍼인텐던트로 임명한다고 전했다. 애스로는 연방준비제도, 파이낸셜 헬스 네트워크, DFS에서의 경력을 바탕으로 금융 접근성 확대와 책임 있는 혁신을 이어갈 적임자로 평가됐다. 해리스는 재임 기간 동안 코인베이스(Coinbase), 제네시스(Genesis) 등 주요 암호화폐 기업을 대상으로 한 집행 조치를 주도했으며, 이더리움(Ethereum)과 솔라나(Solana) 블록체인 기반 스테이블코인 규제 가이드라인을 마련하는 등 기술 규제 체계 구축에도 앞장섰다. 또한 2023년 발간한 블록체인 및 서브 커스터디(하위 수탁) 관계 관련 가이드라인을 통해 디지털 자산 투자자의 보호 기준을 명확히 했다고 강조했다. 그는 “더 많은 기업이 시장에 진입하고 자산 규모와 수탁 관계가 늘어남에 따라 명확한 감독 기준이 필요했다”고 설명했다. 해리스는 폴리티코 인터뷰에서 “잠시 휴식을 취한 뒤 다음 진로를 모색하겠다”며 “내 통장 잔고가 휴식 기간을 결정할 것”이라고 농담을 덧붙였다. *면책 조항: 이 기사는 투자 참고용으로 이를 근거로 한 투자 손실에 대해 책임을 지지 않습니다. 해당 내용은 정보 제공의 목적으로만 해석되어야 합니다.*"
  }
]