[
  {
    "id": "coinreaders_1758192683_0",
    "title": "XRP 노출 다중 암호화폐 ETF, 세계 최초 승인...배리 실버트 \"획기적\"",
    "url": "https://www.coinreaders.com/187406",
    "source": "coinreaders",
    "timestamp": "2025-09-18T19:51:23.205943",
    "risk_level": "HIGH",
    "language": "ko",
    "related_coins": [
      "BTC",
      "ETH",
      "DOGE",
      "SHIB",
      "FLOKI",
      "TRUMP",
      "MAGA"
    ],
    "related_influencers": [
      "Vitalik Buterin",
      "Gary Gensler"
    ],
    "special_categories": [
      "경제적"
    ],
    "content": "시작페이지로l즐겨찾기lRSSl편집 2025.09.18 [19:50] 전체기사l로그인l회원가입lKOR ▲ 엑스알(XRP) 디지털 커런시 그룹(Digital Currency Group) 창립자 배리 실버트(Barry Silbert)가 XRP 익스포저를 포함한 세계 최초 다중 암호화폐 상장지수펀드(ETF) 그레이스케일 디지털 라지 캡 펀드(Grayscale Digital Large Cap Fund, GDLC) 승인을 \"획기적\"이라며 환영했다. 현재 시장은 9억 1,560만 달러 규모의 펀드 출시를 기다리고 있다. 9월 18일(현지시간) 암호화폐 전문 매체 유투데이에 따르면, 실버트는 GDLC 승인 소식에 대해 \"그레이스케일은 지속적으로 선구자 역할을 하며 전통 금융과 디지털 자산을 연결하는 새로운 제품 혁신을 주도하고 있다\"고 평가했다. 그레이스케일 최고경영자 피터 민츠버그(Peter Mintzberg)는 세계 최대 암호화폐 자산운용사 팀이 제품을 시장에 출시하기 위해 \"신속하게\" 작업하고 있다고 밝혔다. GDLC ETF는 비트코인(Bitcoin, BTC)과 이더리움(Ethereum, ETH)뿐만 아니라 엑스알피(XRP), 솔라나(Solana, SOL), 카르다노(Cardano, ADA) 등 여러 주요 알트코인에 노출을 제공하는 콤보 ETF다. XRP는 펀드에서 5.2%의 비중을 차지하며 세 번째로 큰 구성 요소가 되었다. 펀드는 2018년 초 공인 투자자를 위한 사모 상품으로 처음 출시되었으며, 이후 장외거래(OTC) 시장에서 거래되기 시작했다. 지난 7월 초 미국 증권거래위원회(SEC)가 GDLC의 ETF 전환을 승인했지만, 승인 직후 \"검토\"를 위해 갑작스럽게 중단되었다. 9월 17일 기준으로 펀드의 총 자산은 9억 1,560만 달러를 기록했다. 그레이스케일은 SEC를 상대로 한 법정 소송에서 승리하며 암호화폐 ETF 열풍의 촉발제 역할을 한 것으로 평가받고 있다. SEC는 2024년 초 비트코인 ETF를 승인한 후 이더리움 ETF 승인으로 이어졌다. 소소밸류(SoSoValue) 데이터에 따르면 그레이스케일의 주력 상품인 GBTC는 현재 205억 달러 이상의 순자산을 보유하고 있다. 그레이스케일은 암호화폐 ETF 분야에서 선구자적 지위를 유지하며 새로운 제품 혁신을 통해 전통 금융과 디지털 자산 간의 다리 역할을 지속하고 있다. *면책 조항: 이 기사는 투자 참고용으로 이를 근거로 한 투자 손실에 대해 책임을 지지 않습니다. 해당 내용은 정보 제공의 목적으로만 해석되어야 합니다.*"
  },
  {
    "id": "coinreaders_1758192684_1",
    "title": "비트코인 12만 달러·이더리움 5,000달러 도전, 시바이누는 추락 위기?",
    "url": "https://www.coinreaders.com/187403",
    "source": "coinreaders",
    "timestamp": "2025-09-18T19:51:24.085893",
    "risk_level": "HIGH",
    "language": "ko",
    "related_coins": [
      "ETH",
      "BTC",
      "SHIB",
      "DOGE"
    ],
    "related_influencers": [
      "Vitalik Buterin"
    ],
    "special_categories": [
      "경제적"
    ],
    "content": "시작페이지로l즐겨찾기lRSSl편집 2025.09.18 [19:50] 전체기사l로그인l회원가입lKOR ▲ 이더리움(ETH), 비트코인(BTC) 암호화폐 시장이 비트코인(Bitcoin, BTC), 시바이누(Shiba Inu, SHIB), 이더리움(Ethereum, ETH) 등 주요 자산을 중심으로 회복세 신호를 내고 있다. 기술적 지표와 패턴이 강세를 뒷받침하면서 향후 장기 상승으로 이어질 수 있다는 전망이 제기된다. 9월 18일(현지시간) 암호화폐 전문 매체 유투데이에 따르면, 시바이누는 0.0000129달러 부근에서 50일·100일·200일 이동평균선이 밀집한 구간에 갇혀 있으며, 이는 강세와 약세 세력이 맞붙는 핵심 전장이 되고 있다. 상단 저항선은 0.0000140달러, 하단 지지선은 0.0000124달러로 설정됐다. 저항을 돌파하면 0.0000160달러, 나아가 0.0000200달러까지 오를 수 있으나, 지지선이 붕괴되면 0.0000100달러로 밀리며 시가총액에 또 다른 0이 추가될 수 있다. 비트코인은 조용한 흐름 속에서 11만 6,300달러 부근에 거래되고 있다. 200일 이동평균선 10만 5,500달러가 강력한 장기 지지선으로 작용하고 있으며, 단기적으로는 11만 4,300달러와 11만 3,800달러가 추가 지지 구간이다. 상대강도지수(RSI)는 59로 중립을 유지해 과매수 구간에 진입하지 않은 상태다. 주요 저항은 11만 8,000~12만 달러이며, 이를 넘어서면 12만 5,000~13만 달러 구간이 목표로 제시된다. 이더리움은 현재 4,490달러에 거래되며 50일·100일 이동평균선 위를 유지하고 있다. 이는 최근 조정에도 불구하고 강세 구조를 유지하는 핵심 요인이다. 상대강도지수는 53으로 여전히 중립 상태에 있어 매수 압력이 유입될 경우 추가 상승 여력이 충분하다. 이더리움의 심리적 목표 가격은 5,000달러이며, 단기 저항 구간인 4,600~4,700달러를 돌파하면 매수세가 몰리며 5,200~5,400달러까지 이어질 가능성이 있다. 반대로 4,200달러 지지를 잃을 경우 200일 이동평균선이 위치한 3,760달러까지 후퇴할 수 있다. *면책 조항: 이 기사는 투자 참고용으로 이를 근거로 한 투자 손실에 대해 책임을 지지 않습니다. 해당 내용은 정보 제공의 목적으로만 해석되어야 합니다.*"
  },
  {
    "id": "coinreaders_1758192687_5",
    "title": "\"몇 주 안에 폭발한다\"...SEC 결정에 암호화폐 ETF 시대 개막",
    "url": "https://www.coinreaders.com/187389",
    "source": "coinreaders",
    "timestamp": "2025-09-18T19:51:27.037819",
    "risk_level": "HIGH",
    "language": "ko",
    "related_coins": [
      "ETH",
      "BTC",
      "DOGE",
      "SHIB",
      "FLOKI",
      "MAGA"
    ],
    "related_influencers": [
      "Gary Gensler",
      "Vitalik Buterin"
    ],
    "special_categories": [
      "경제적"
    ],
    "content": "시작페이지로l즐겨찾기lRSSl편집 2025.09.18 [19:50] 전체기사l로그인l회원가입lKOR ▲ 엑스알피(XRP), 미국 증권거래위원회(SEC)/챗gpt 생성 이미지 미국 증권거래위원회(SEC)가 암호화폐 현물 ETF 상장 절차를 간소화하는 일반 상장 기준을 승인하며, 암호화폐 시장에 새로운 전환점을 열었다. 이번 결정으로 ETF 승인은 개별 심사 방식에서 벗어나며, 다수의 디지털 자산 ETF가 수 주 내로 시장에 진입할 수 있게 됐다. 9월 18일(현지시간) 암호화폐 전문 매체 비인크립토에 따르면, 그레이스케일(Grayscale)은 새 규정 승인 직후 자사의 디지털 대형주 펀드(GDLC)에 대한 거래 허가를 획득했다. 해당 펀드는 비트코인(Bitcoin, BTC), 이더리움(Ethereum, ETH), 엑스알피(XRP), 솔라나(Solana, SOL), 카르다노(Cardano, ADA)를 포함한 첫 다자산 기반 상장지수상품으로, 미국 시장에서 포트폴리오 다각화의 첫 사례를 만들었다. 그레이스케일 최고경영자 피터 민츠버그(Peter Mintzberg)는 “비트코인, 이더리움, XRP, 솔라나, 카르다노를 포함한 최초의 멀티 암호화폐 ETP가 승인됐다”며 신속한 시장 진입을 예고했다. 블룸버그 애널리스트 에릭 발추나스(Eric Balchunas)는 이번 조치로 12~15종의 암호화폐가 ETF 자격을 얻게 됐다고 설명했다. 다만 조건은 코인베이스(Coinbase) 파생상품 거래소에서 최소 6개월 이상 규제 선물 거래 이력이 있어야 한다. 이에 따라 도지코인(Dogecoin, DOGE), 라이트코인(Litecoin, LTC), 체인링크(Chainlink, LINK) 등도 승인을 받을 가능성이 높다. 솔라나는 지난 2월 선물이 출시돼 8월 19일부터 자격 요건을 충족했다. 체인링크 커뮤니티의 잭 라인스(Zach Rynes)는 이미 비트와이즈(Bitwise)와 그레이스케일이 관련 신청서를 제출했다며 LINK ETF 가능성을 언급했다. 라이트코인 재단도 새로운 규정이 LTC 상장을 위한 법적 근거를 제공한다고 밝혔다. 해데라(Hedera, HBAR) 역시 ETF 출범 후보로 지목되며 시장 관심을 끌고 있다. ETF 애널리스트 제임스 세이파트(James Seyffart)는 “몇 주 안에 시장이 본격적으로 움직일 것”이라고 전하며, 이번 결정이 암호화폐 ETF의 대중화를 촉진할 규제 명확성과 투자자 접근성을 동시에 제공한다고 평가했다. *면책 조항: 이 기사는 투자 참고용으로 이를 근거로 한 투자 손실에 대해 책임을 지지 않습니다. 해당 내용은 정보 제공의 목적으로만 해석되어야 합니다.*"
  },
  {
    "id": "coinreaders_1758192689_9",
    "title": "리플, 1,400만 RLUSD 신규 발행…시총 4억 6,900만 달러 돌파",
    "url": "https://www.coinreaders.com/170197",
    "source": "coinreaders",
    "timestamp": "2025-09-18T19:51:29.928256",
    "risk_level": "HIGH",
    "language": "ko",
    "related_coins": [
      "ETH",
      "BTC"
    ],
    "related_influencers": [
      "Vitalik Buterin",
      "Gary Gensler"
    ],
    "special_categories": [
      "경제적",
      "환경적"
    ],
    "content": "시작페이지로l즐겨찾기lRSSl편집 2025.09.18 [19:50] 전체기사l로그인l회원가입lKOR ▲ XRP(엑스알피, 리플) © 7월 2일(현지시간) 암호화폐 전문매체 유투데이에 따르면, 리플(Ripple)이 자사 스테이블코인 RLUSD 1,400만 개를 추가 발행했다. 이번 발행은 이더리움(Ethereum) 블록체인 기반 RLUSD 트레저리를 통해 이뤄졌으며, 이는 2025년 7월 들어 첫 번째 발행 사례다. 이번 RLUSD 발행은 시장 내 유통량 확대 전략의 일환으로, 최근 암호화폐 시장 전반의 상승 흐름에 발맞춰 리플 생태계 내 스테이블코인 수요도 함께 증가한 것으로 보인다. 발행 직후 RLUSD의 시가총액은 전일 대비 3.09% 증가해 4억 6,922만 달러를 기록했다. 다만 거래량은 하루 전 260% 급등한 데 이어, 이날 들어 59.51% 급감하며 높은 변동성을 보였다. 코인마켓캡에 따르면 이는 전체 암호화폐 시장 내 급등락 흐름에 따른 반응으로 풀이된다. RLUSD는 2024년 말 출시된 이후 빠르게 성장하며, 현재까지 누적 공급량이 4억 6,924만 달러에 달한다. 특히 최근 두바이 국제금융센터(DIFC)로부터 규제 승인을 획득하면서 글로벌 결제 시장에서의 활용 가능성도 확대되고 있다. 리플은 SEC와의 법적 분쟁 이후 기업 대상 결제, 실물 자산 토큰화 등 실용적 영역에서의 확장을 본격화하고 있다. 이 과정에서 RLUSD는 기관 결제와 국경 간 송금에 특화된 스테이블코인으로 자리잡으며, XRP 생태계 전반의 성장 촉매 역할을 하고 있다. 이번 발행과 규제 승인 흐름은 리플 생태계의 글로벌 확장을 가속화하는 동시에, XRP의 시장 신뢰도를 높이는 데 긍정적으로 작용할 것으로 보인다. *면책 조항: 이 기사는 투자 참고용으로 이를 근거로 한 투자 손실에 대해 책임을 지지 않습니다. 해당 내용은 정보 제공의 목적으로만 해석되어야 합니다.*"
  },
  {
    "id": "coinreaders_1758192691_11",
    "title": "2028년 스테이블코인 2조 달러 시대, 트론(TRX)이 중심에 설까",
    "url": "https://www.coinreaders.com/166530",
    "source": "coinreaders",
    "timestamp": "2025-09-18T19:51:31.842002",
    "risk_level": "HIGH",
    "language": "ko",
    "related_coins": [
      "ETH",
      "BTC"
    ],
    "related_influencers": [
      "Vitalik Buterin"
    ],
    "special_categories": [
      "경제적"
    ],
    "content": "시작페이지로l즐겨찾기lRSSl편집 2025.09.18 [19:50] 전체기사l로그인l회원가입lKOR ▲ 트론(Tron, TRX) ©코인리더스 고래 투자자들이 테더(USDT) 대량 전송에 트론(TRON) 네트워크를 적극 활용하면서, 트론이 글로벌 스테이블코인 흐름의 중심으로 부상하고 있다. 6월 14일(현지시간) 암호화폐 전문매체 비인크립토에 따르면, 트론 네트워크에서는 지난 5월 한 달 동안 총 6945억 4,000만 달러 규모의 USDT가 전송됐으며, 이 중 약 60%인 4112억 달러는 100만 달러 이상 규모의 고액 거래였다. 이는 역대 최고 기록이다. 현재 트론의 USDT 공급량은 6개월 새 36% 증가해 580억 달러에서 790억 달러로 확대됐다. 하루 평균 240만 건 이상의 USDT 전송이 이뤄지고 있으며, 일일 전송량은 237억 달러에 달해 이더리움을 넘어서는 글로벌 1위 스테이블코인 전송 네트워크로 자리 잡았다. 크립토퀀트의 애널리스트 JA 마르툰(JA Maartunn)은 “스테이블코인이 암호화폐 채택의 핵심 요소로 떠오르고 있다”며, 최근 서클(Circle)의 IPO도 이러한 흐름을 반영한다고 분석했다. 그는 트론에서의 대규모 거래 중심 전송 패턴이 기관 투자자 및 고액 자금 흐름을 보여주는 지표라고 덧붙였다. 트론의 기본 토큰 TRX 또한 5월에 4903억 개의 전송량을 기록하며 사상 최고치를 경신했다. 이는 당시 기준으로 1,212억 달러에 해당하는 수치다. 올해 상반기 내내 트론은 이더리움을 제치고 USDT 총 공급량과 일일 거래 건수에서 모두 우위를 유지하고 있다. 미 재무부는 2028년까지 스테이블코인 시장이 2조 달러 규모에 도달할 것으로 예상하고 있으며, 트론의 빠른 성장세는 이 같은 전망 속에서 핵심 결제 인프라로서의 입지를 강화하고 있다. *면책 조항: 이 기사는 투자 참고용으로 이를 근거로 한 투자 손실에 대해 책임을 지지 않습니다. 해당 내용은 정보 제공의 목적으로만 해석되어야 합니다.*"
  }
]