{
  "timestamp": "2025-09-22T06:12:13.035574",
  "by_coin": {
    "DOGE": [
      {
        "id": "coinreaders_1758488522_0",
        "title": "시바이누, 정체 깨는 신호 터졌다...대규모 반등 임박",
        "url": "https://www.coinreaders.com/187916",
        "source": "coinreaders",
        "timestamp": "2025-09-22T06:02:02.127118",
        "risk_level": "LOW",
        "related_influencers": [],
        "special_categories": [
          "경제적"
        ]
      }
    ],
    "SHIB": [
      {
        "id": "coinreaders_1758488522_0",
        "title": "시바이누, 정체 깨는 신호 터졌다...대규모 반등 임박",
        "url": "https://www.coinreaders.com/187916",
        "source": "coinreaders",
        "timestamp": "2025-09-22T06:02:02.127118",
        "risk_level": "LOW",
        "related_influencers": [],
        "special_categories": [
          "경제적"
        ]
      }
    ]
  },
  "by_influencer": {},
  "high_risk": [],
  "total_count": 1,
  "source_file": "news/all_news_20250922_0602.json"
}